ovos_tts_plugin_edge_tts/__init__.py
ovos_tts_plugin_edge_tts/version.py
ovos_tts_plugin_edge_tts-0.2.2.dist-info/LICENSE.txt
ovos_tts_plugin_edge_tts-0.2.2.dist-info/METADATA
ovos_tts_plugin_edge_tts-0.2.2.dist-info/WHEEL
ovos_tts_plugin_edge_tts-0.2.2.dist-info/entry_points.txt
ovos_tts_plugin_edge_tts-0.2.2.dist-info/top_level.txt
ovos_tts_plugin_edge_tts-0.2.2.dist-info/zip-safe
ovos_tts_plugin_edge_tts-0.2.2.dist-info/RECORD
