Metadata-Version: 2.1
Name: ovos-tts-plugin-edge-tts
Version: 0.2.2
Summary: A tts plugin for OpenVoiceOS, using EdgeTTS
Home-page: https://github.com/OpenVoiceOS/ovos-tts-plugin-edge-tts
Author: jarbasAi
Author-email: jarbasai@mailfence.com
License: Apache-2.0
Keywords: ovos plugin tts edge-tts
Classifier: Development Status :: 3 - Alpha
Classifier: Intended Audience :: Developers
Classifier: Topic :: Text Processing :: Linguistic
Classifier: License :: OSI Approved :: Apache Software License
Classifier: Programming Language :: Python :: 3.7
License-File: LICENSE.txt
Requires-Dist: ovos-plugin-manager<2.0.0,>=1.0.0
Requires-Dist: edge-tts>=6.1.9
